xmodels/constraints.py
xmodels/fields.py
xmodels/models.py
xmodels/utils.py
xmodels/__init__.py
xmodels/iso8601/datetimestamps.py
xmodels/iso8601/regexs.py
xmodels/iso8601/timezones.py
xmodels/iso8601/utility.py
xmodels/iso8601/__init__.py
xmodels-0.1.0.dist-info/DESCRIPTION.rst
xmodels-0.1.0.dist-info/METADATA
xmodels-0.1.0.dist-info/metadata.json
xmodels-0.1.0.dist-info/RECORD
xmodels-0.1.0.dist-info/top_level.txt
xmodels-0.1.0.dist-info/WHEEL
