Metadata-Version: 2.0
Name: xmodels
Version: 0.1.0
Summary: Python models for creation, parsing and validation of XML documents.
Home-page: https://github.com/berndca/xmodels
Author: Bernd Meyer
Author-email: berndca@gmail.com
License: BSD
Keywords: xml schema json
Platform: UNKNOWN
Classifier: Development Status :: 2 - Pre-Alpha
Classifier: Intended Audience :: Developers
Classifier: License :: OSI Approved :: BSD License
Classifier: Natural Language :: English
Classifier: Programming Language :: Python :: 2
Classifier: Programming Language :: Python :: 2.6
Classifier: Programming Language :: Python :: 2.7
Classifier: Programming Language :: Python :: 3
Classifier: Programming Language :: Python :: 3.3
Classifier: Programming Language :: Python :: 3.4
Classifier: Programming Language :: Python :: Implementation :: CPython
Classifier: Programming Language :: Python :: Implementation :: PyPy
Requires-Dist: six
